README.md
setup.py
umd_python_cas/__init__.py
umd_python_cas/umd_python_cas.py
umd_python_cas.egg-info/PKG-INFO
umd_python_cas.egg-info/SOURCES.txt
umd_python_cas.egg-info/dependency_links.txt
umd_python_cas.egg-info/requires.txt
umd_python_cas.egg-info/top_level.txt