Metadata-Version: 1.1
Name: umd-python-cas
Version: 1.0.0
Summary: A python client to access the University of Maryland Central Authentication Services (CAS) remote instance.
Home-page: https://github.com/umd-python-cas/umd-python-cas
Author: Jacob (Coby) Winfield
Author-email: coby.winfield@gmail.com
License: MIT
Platform: UNKNOWN
Classifier: Development Status :: 1 - Planning
Classifier: Intended Audience :: Science/Research
Classifier: License :: OSI Approved :: MIT License
Classifier: Operating System :: POSIX :: Linux
Classifier: Programming Language :: Python :: 2
Classifier: Programming Language :: Python :: 2.7
Classifier: Programming Language :: Python :: 3
Classifier: Programming Language :: Python :: 3.4
Classifier: Programming Language :: Python :: 3.5
